ddcLogs/.env.example
ddcLogs/__init__.py
ddcLogs/basic_log.py
ddcLogs/log_utils.py
ddcLogs/settings.py
ddcLogs/size_rotating.py
ddcLogs/timed_rotating.py
ddclogs-3.0.12.dist-info/LICENSE
ddclogs-3.0.12.dist-info/METADATA
ddclogs-3.0.12.dist-info/WHEEL
ddclogs-3.0.12.dist-info/RECORD
