Metadata-Version: 2.1
Name: ddcLogs
Version: 3.0.12
Summary: Easy logs with rotations
Home-page: https://pypi.org/project/ddcLogs
License: MIT
Keywords: python3,python-3,python,log,logging,logger,logutils,log-utils,ddcLogs
Author: Daniel Costa
Author-email: danieldcsta@gmail.com
Maintainer: Daniel Costa
Requires-Python: >=3.10,<4.0
Classifier: Development Status :: 5 - Production/Stable
Classifier: Environment :: Other Environment
Classifier: Intended Audience :: Developers
Classifier: License :: OSI Approved :: MIT License
Classifier: Natural Language :: English
Classifier: Operating System :: OS Independent
Classifier: Programming Language :: Python :: 3
Classifier: Programming Language :: Python :: 3.10
Classifier: Programming Language :: Python :: 3.11
Classifier: Programming Language :: Python :: 3.12
Classifier: Programming Language :: Python :: 3.13
Classifier: Programming Language :: Python :: 3 :: Only
Classifier: Topic :: Software Development :: Libraries :: Python Modules
Requires-Dist: pydantic-settings (>=2.6.1,<3.0.0)
Requires-Dist: python-dotenv (>=1.0.1,<2.0.0)
Requires-Dist: pytz (>=2024.2,<2025.0)
Project-URL: Repository, https://github.com/ddc/ddcLogs
